<?xml version="1.0" encoding="UTF-8" standalone="no"?>
<!--
  This is a sample configuration to recursively migrate a local directory to an ECS S3 bucket.
  It uses 32 threads, verifies data using MD5 checksums and tracks status of all objects in a database table.
  -->
<syncConfig xmlns="http://www.emc.com/ecs/sync/model"
            xmlns:xsi="http://www.w3.org/2001/XMLSchema-instance"
            xsi:schemaLocation="http://www.emc.com/ecs/sync/model model.xsd">
    <options>
        <threadCount>32</threadCount>
        <verify>true</verify>

        <!-- uncomment the following if you are *not* submitting to the ecs-sync service running on the OVA -->
        <!--
        <dbConnectString>jdbc:mysql://localhost:3306/ecs_sync?user=ecssync&amp;autoReconnect=true&amp;characterEncoding=UTF-8</dbConnectString>
        <dbEncPassword>Z0TUQ+sciX2fp623Iu9LcQ==</dbEncPassword>
        -->
        <dbTable>files_to_ecs</dbTable>
        <!-- comment above and uncomment below if you are *not* connecting to a mysql DB -->
        <!--
        <dbFile>files_to_ecs.db</dbFile>
        -->
    </options>

    <source>
        <filesystemConfig>
            <path>/path/to/my-files</path>
        </filesystemConfig>
    </source>

    <target>
        <ecsS3Config>
            <protocol>http</protocol>
            <vdcs>vegas(10.10.10.11,10.10.10.12)</vdcs>
            <vdcs>vegas(10.10.20.11,10.10.20.12)</vdcs>
            <port>9020</port>
            <accessKey>ace7d3da351242bcb095eb841ad5d371</accessKey>
            <secretKey>HkAyrXoEYUQ3VCMCaaViS1t5pdS=</secretKey>
            <bucketName>my-bucket</bucketName>
            <createBucket>true</createBucket>
            <!-- this will preserve directories (including empty ones) for later restoration -->
            <preserveDirectories>true</preserveDirectories>
        </ecsS3Config>
    </target>
</syncConfig>
